stats_comp/__init__.py
stats_comp/analysis_c.py
stats_comp/analysis_cc.py
stats_comp/analysis_multi.py
stats_comp/analysis_n.py
stats_comp/analysis_nc.py
stats_comp/analysis_nn.py
stats_comp/lttb.py
stats_comp/utilities.py
stats_comp-1.0.0.dist-info/METADATA
stats_comp-1.0.0.dist-info/RECORD
stats_comp-1.0.0.dist-info/WHEEL
stats_comp-1.0.0.dist-info/top_level.txt
